EZCommandLine/__init__.py
EZCommandLine-1.0.0.dist-info/LICENSE
EZCommandLine-1.0.0.dist-info/METADATA
EZCommandLine-1.0.0.dist-info/WHEEL
EZCommandLine-1.0.0.dist-info/top_level.txt
EZCommandLine-1.0.0.dist-info/RECORD
