Metadata-Version: 2.1
Name: EZCommandLine
Version: 1.0.0
Summary: A package to easily create a command interpreter for a console-like app
Author: Fastattack
License: MIT License
Project-URL: Homepage, https://github.com/fastattackv/EZCommandLine
Project-URL: Issues, https://github.com/fastattackv/EZCommandLine/Issues
Classifier: Programming Language :: Python :: 3
Classifier: License :: OSI Approved :: MIT License
Classifier: Operating System :: OS Independent
Requires-Python: >=3.7
License-File: LICENSE
